kobert4ner/__init__.py
kobert4ner/_model.py
kobert4ner/_preprocess.py
kobert4ner/_tokenization_kobert.py
kobert4ner/_utils.py
kobert4ner-0.0.1.dist-info/LICENSE
kobert4ner-0.0.1.dist-info/METADATA
kobert4ner-0.0.1.dist-info/WHEEL
kobert4ner-0.0.1.dist-info/top_level.txt
kobert4ner-0.0.1.dist-info/RECORD
